[{"q":"<p>You are programming a microcontroller with the help of embedded C language to check if the year entered is a leap year or not. The code used is given below. You are required to optimize the code into a code that uses a single if condition.</p>\n\n<p><strong>Code</strong></p>\n\n<pre class=\"prettyprint\"><code>#include &lt;stdio.h&gt;\n \nint main()\n{\n  int year;\n \n  scanf(\"%d\", &amp;year);\n \n  if ( year%400 == 0)\n    printf(\"%d is a leap year.\\n\", year);\n  else if ( year%100 == 0)\n    printf(\"%d is not a leap year.\\n\", year);\n  else if ( year%4 == 0 )\n    printf(\"%d is a leap year.\\n\", year);\n  else\n    printf(\"%d is not a leap year.\\n\", year);  \n \n  return 0;\n}</code></pre>\n\n<p>Which of the following if conditions will produce the correct output for the given scenario:</p>\n\n<p><strong>If conditions</strong></p>\n\n<ol>\n\t<li>\n\t<pre class=\"prettyprint\"><code>if(((year%4==0) &amp;&amp; (year%400==0)) &amp;&amp; (year%100!=0))\n     printf(\"%d is a leap year.\\n\", year);\nelse\n    printf(\"%d is not a leap year.\\n\", year);\n</code></pre>\n\n\t<p>&nbsp;</p>\n\t</li>\n\t<li>\n\t<pre class=\"prettyprint\"><code>if((year%4==0) || ((year%400==0) &amp;&amp; (year%100!=0)))\n     printf(\"%d is a leap year.\\n\", year);\nelse\n    printf(\"%d is not a leap year.\\n\", year);\n</code></pre>\n\n\t<p>&nbsp;</p>\n\t</li>\n\t<li>\n\t<pre class=\"prettyprint\"><code>if(((year%4==0) || (year%400==0)) || (year%100!=0))\n     printf(\"%d is a leap year.\\n\", year);\nelse\n    printf(\"%d is not a leap year.\\n\", year);\n</code></pre>\n\n\t<p>&nbsp;</p>\n\t</li>\n\t<li>\n\t<pre class=\"prettyprint\"><code> if(((year % 4 == 0) &amp;&amp; (year % 100!= 0)) || (year%400 == 0))\n     printf(\"%d is a leap year.\\n\", year);\nelse\n    printf(\"%d is not a leap year.\\n\", year);\n</code></pre>\n\t</li>\n</ol>","a":[{"id":1768894,"option":"1","correct":false},{"id":1768895,"option":"2","correct":false},{"id":1768896,"option":"3","correct":false},{"id":1768897,"option":"4","correct":true}]}]