[{"q":"<p>In Flask, the <strong>instance</strong> folder acts like a holder bin for ________________________________________.</p>","a":[{"id":129504,"option":"Database files","correct":false},{"id":129505,"option":"Session files","correct":true},{"id":129506,"option":"All of these","correct":false},{"id":129507,"option":"None of these","correct":false}]},{"q":"<p>In Flask, which of the following parameters is passed in an <strong>open_session()</strong> method?</p>","a":[{"id":129572,"option":"Response ","correct":false},{"id":129573,"option":"Request ","correct":true},{"id":129574,"option":"Both of these","correct":false},{"id":129575,"option":"Params","correct":false}]},{"q":"<p>In Flask, <strong>open_session()</strong> method is used to __________________.</p>","a":[{"id":129576,"option":"Open a session ","correct":false},{"id":129577,"option":"Create a session ","correct":false},{"id":129578,"option":"Open and create a session ","correct":true},{"id":129579,"option":"Start a session ","correct":false}]}]